actinia_parallel_plugin/__init__.py
actinia_parallel_plugin/endpoints.py
actinia_parallel_plugin/api/__init__.py
actinia_parallel_plugin/api/batch.py
actinia_parallel_plugin/api/job.py
actinia_parallel_plugin/api/parallel_ephemeral_processing.py
actinia_parallel_plugin/apidocs/__init__.py
actinia_parallel_plugin/apidocs/batch.py
actinia_parallel_plugin/apidocs/jobs.py
actinia_parallel_plugin/apidocs/examples/__init__.py
actinia_parallel_plugin/apidocs/examples/batchjob_post_response_example.json
actinia_parallel_plugin/apidocs/examples/jobs_get_docs_response_example.json
actinia_parallel_plugin/core/__init__.py
actinia_parallel_plugin/core/batches.py
actinia_parallel_plugin/core/ephemeral_processing.py
actinia_parallel_plugin/core/jobs.py
actinia_parallel_plugin/core/jobtable.py
actinia_parallel_plugin/core/parallel_processing_job.py
actinia_parallel_plugin/core/parallel_resource_base.py
actinia_parallel_plugin/model/__init__.py
actinia_parallel_plugin/model/batch.py
actinia_parallel_plugin/model/batch_process_chain.py
actinia_parallel_plugin/model/jobtable.py
actinia_parallel_plugin/resources/__init__.py
actinia_parallel_plugin/resources/config.py
actinia_parallel_plugin/resources/logging.py
actinia_parallel_plugin/resources/migrations/0000.info.py
actinia_parallel_plugin/resources/migrations/__init__.py
actinia_parallel_plugin-1.2.0.dist-info/licenses/LICENSE.txt
actinia_parallel_plugin-1.2.0.dist-info/METADATA
actinia_parallel_plugin-1.2.0.dist-info/WHEEL
actinia_parallel_plugin-1.2.0.dist-info/top_level.txt
actinia_parallel_plugin-1.2.0.dist-info/RECORD
